vtmmpy/__init__.py
vtmmpy-1.0.11.dist-info/LICENSE
vtmmpy-1.0.11.dist-info/METADATA
vtmmpy-1.0.11.dist-info/WHEEL
vtmmpy-1.0.11.dist-info/RECORD
