Metadata-Version: 2.1
Name: vtmmpy
Version: 1.0.11
Summary: A vectorized implementation of the transfer matrix method
Home-page: https://github.com/AI-Tony/vtmmpy/tree/main
Author: Tony
Author-email: tk_87@hotmail.com
Requires-Python: >=3.6,<4.0
Classifier: Programming Language :: Python :: 3
Classifier: Programming Language :: Python :: 3.6
Classifier: Programming Language :: Python :: 3.7
Classifier: Programming Language :: Python :: 3.8
Classifier: Programming Language :: Python :: 3.9
Classifier: Programming Language :: Python :: 3.10
Classifier: Programming Language :: Python :: 3.11
Requires-Dist: numpy
Requires-Dist: pandas
Requires-Dist: refidx
Project-URL: Repository, https://github.com/AI-Tony/vtmmpy/tree/main
